jupyter_scheduler/__init__.py
jupyter_scheduler/_version.py
jupyter_scheduler/environments.py
jupyter_scheduler/exceptions.py
jupyter_scheduler/executors.py
jupyter_scheduler/extension.py
jupyter_scheduler/handlers.py
jupyter_scheduler/job_files_manager.py
jupyter_scheduler/models.py
jupyter_scheduler/orm.py
jupyter_scheduler/parameterize.py
jupyter_scheduler/scheduler.py
jupyter_scheduler/task_runner.py
jupyter_scheduler/utils.py
jupyter_scheduler/labextension/package.json
jupyter_scheduler/labextension/schemas/@jupyterlab/scheduler/package.json.orig
jupyter_scheduler/labextension/schemas/@jupyterlab/scheduler/plugin.json
jupyter_scheduler/labextension/static/122.b4ab1a65371e7c0f8bdd.js
jupyter_scheduler/labextension/static/167.cba40e27a7d16c77219d.js
jupyter_scheduler/labextension/static/177.3502ccdd2c25548ad980.js
jupyter_scheduler/labextension/static/2.db271f70c2da418b0cdc.js
jupyter_scheduler/labextension/static/2.db271f70c2da418b0cdc.js.LICENSE.txt
jupyter_scheduler/labextension/static/378.09c219e101bb822ddfcf.js
jupyter_scheduler/labextension/static/458.d59c5307102faf5c19a8.js
jupyter_scheduler/labextension/static/470.da7e4fe7177a2696e6be.js
jupyter_scheduler/labextension/static/470.da7e4fe7177a2696e6be.js.LICENSE.txt
jupyter_scheduler/labextension/static/572.f6d1aed3ed595a922757.js
jupyter_scheduler/labextension/static/613.17512dda5aad1f2a390f.js
jupyter_scheduler/labextension/static/687.e4421b30aab66f8929fd.js
jupyter_scheduler/labextension/static/687.e4421b30aab66f8929fd.js.LICENSE.txt
jupyter_scheduler/labextension/static/747.8e4a60162d1a81804893.js
jupyter_scheduler/labextension/static/936.3b729444b6907e91e130.js
jupyter_scheduler/labextension/static/985.6d0ae2c14c2cd734ba32.js
jupyter_scheduler/labextension/static/remoteEntry.2f95ce0356771ef2f962.js
jupyter_scheduler/labextension/static/style.js
jupyter_scheduler/labextension/static/third-party-licenses.json
jupyter_scheduler/pydantic_v1/__init__.py
jupyter_scheduler/pydantic_v1/dataclasses.py
jupyter_scheduler-2.11.0.dist-info/METADATA
jupyter_scheduler-2.11.0.dist-info/WHEEL
jupyter_scheduler-2.11.0.dist-info/licenses/LICENSE
jupyter_scheduler-2.11.0.dist-info/RECORD
